LICENSE
README.md
setup.py
UniTok.egg-info/PKG-INFO
UniTok.egg-info/SOURCES.txt
UniTok.egg-info/dependency_links.txt
UniTok.egg-info/entry_points.txt
UniTok.egg-info/requires.txt
UniTok.egg-info/top_level.txt
UniTokv3/__init__.py
UniTokv3/__main__.py
UniTokv3/cols.py
UniTokv3/column.py
UniTokv3/fut.py
UniTokv3/global_setting.py
UniTokv3/meta.py
UniTokv3/unidep.py
UniTokv3/unitok.py
UniTokv3/vocab.py
UniTokv3/vocabs.py
UniTokv3/analysis/__init__.py
UniTokv3/analysis/lengths.py
UniTokv3/analysis/plot.py
UniTokv3/tok/__init__.py
UniTokv3/tok/bert_tok.py
UniTokv3/tok/ent_tok.py
UniTokv3/tok/id_tok.py
UniTokv3/tok/number_tok.py
UniTokv3/tok/seq_tok.py
UniTokv3/tok/split_tok.py
UniTokv3/tok/tok.py
unitok/__init__.py
unitok/__main__.py
unitok/feature.py
unitok/job.py
unitok/meta.py
unitok/selector.py
unitok/status.py
unitok/unitok.py
unitok/tokenizer/__init__.py
unitok/tokenizer/base_tokenizer.py
unitok/tokenizer/digit_tokenizer.py
unitok/tokenizer/entity_tokenizer.py
unitok/tokenizer/glove_tokenizer.py
unitok/tokenizer/split_tokenizer.py
unitok/tokenizer/transformers_tokenizer.py
unitok/tokenizer/union_tokenizer.py
unitok/tokenizer/unknown_tokenizer.py
unitok/utils/__init__.py
unitok/utils/class_pool.py
unitok/utils/data.py
unitok/utils/function.py
unitok/utils/instance.py
unitok/utils/map.py
unitok/utils/space.py
unitok/utils/symbol.py
unitok/utils/verbose.py
unitok/utils/handler/__init__.py
unitok/utils/handler/json_handler.py
unitok/utils/handler/pkl_handler.py
unitok/utils/hub/__init__.py
unitok/utils/hub/hub.py
unitok/utils/hub/param_hub.py
unitok/utils/index_set/__init__.py
unitok/utils/index_set/feature_set.py
unitok/utils/index_set/index_set.py
unitok/utils/index_set/job_set.py
unitok/utils/index_set/tokenizer_set.py
unitok/utils/index_set/vocabulary_set.py
unitok/vocabulary/__init__.py
unitok/vocabulary/counter.py
unitok/vocabulary/vocabulary.py