Metadata-Version: 2.1
Name: UniTok
Version: 4.4.0
Summary: Unified Tokenizer
Home-page: https://github.com/Jyonn/UnifiedTokenizer
Author: Jyonn Liu
Author-email: liu@qijiong.work
License: MIT Licence
Keywords: token,tokenizer,NLP,transformers,glove,bert,llama
Platform: any
License-File: LICENSE
Requires-Dist: termplot==0.0.2
Requires-Dist: tqdm
Requires-Dist: numpy
Requires-Dist: pandas
Requires-Dist: transformers
Requires-Dist: oba
Requires-Dist: prettytable
Requires-Dist: rich
